<buttons defaulttype="Button">
  <button caption="Графік подій" hint="Перегляд графіку подій по вибраному договору застави" id="bEv">
    <command type="Redirect" checkselectedrow="true" url="dynform.aspx?form=frm_grt_dog_events">
      <parameters>
        <parameter type="DataField" name="DEAL_ID"></parameter>
      </parameters>
    </command>
  </button>
  <button caption="Закрити договір" confirmmessage="Договір буде закрито. Підтвердіть операцію" hint="Закрити вибраний договір" id="btnClose" >
    <command type="PlSqlBlock" checkselectedrow="true" successmessage="Договір закрито">
      <sql>
        begin grt_mgr.close_deal(:DEAL_ID); end;
      </sql>
      <parameters>
        <parameter type="DataField" name="DEAL_ID"></parameter>
      </parameters>
    </command>  
  </button>
</buttons>